odoo/addons/event_mail/README.rst
odoo/addons/event_mail/__init__.py
odoo/addons/event_mail/__manifest__.py
odoo/addons/event_mail/i18n/es.po
odoo/addons/event_mail/i18n/event_mail.pot
odoo/addons/event_mail/i18n/fr.po
odoo/addons/event_mail/i18n/it.po
odoo/addons/event_mail/models/__init__.py
odoo/addons/event_mail/models/event.py
odoo/addons/event_mail/models/event_mail.py
odoo/addons/event_mail/models/event_type.py
odoo/addons/event_mail/models/res_company.py
odoo/addons/event_mail/models/res_config_settings.py
odoo/addons/event_mail/readme/CONTRIBUTORS.rst
odoo/addons/event_mail/readme/DESCRIPTION.rst
odoo/addons/event_mail/readme/USAGE.rst
odoo/addons/event_mail/security/ir.model.access.csv
odoo/addons/event_mail/static/description/icon.png
odoo/addons/event_mail/static/description/index.html
odoo/addons/event_mail/tests/__init__.py
odoo/addons/event_mail/tests/test_event_mail.py
odoo/addons/event_mail/views/event_mail_view.xml
odoo/addons/event_mail/views/event_view.xml
odoo/addons/event_mail/views/res_config_view.xml
odoo13_addon_event_mail-13.0.1.0.1.dev8.dist-info/METADATA
odoo13_addon_event_mail-13.0.1.0.1.dev8.dist-info/WHEEL
odoo13_addon_event_mail-13.0.1.0.1.dev8.dist-info/top_level.txt
odoo13_addon_event_mail-13.0.1.0.1.dev8.dist-info/RECORD
